peacasso/__init__.py
peacasso/applications.py
peacasso/cli.py
peacasso/datamodel.py
peacasso/generator.py
peacasso/pipelines.py
peacasso/utils.py
peacasso/version.py
peacasso/web/__init__.py
peacasso/web/backend/__init__.py
peacasso/web/backend/app.py
peacasso/web/backend/ui/1e4e30ccbb5ab1f63166ed9953f05f177bc9b101-e3da20cfdca65c9db3a3.js
peacasso/web/backend/ui/1e4e30ccbb5ab1f63166ed9953f05f177bc9b101-e3da20cfdca65c9db3a3.js.LICENSE.txt
peacasso/web/backend/ui/1e4e30ccbb5ab1f63166ed9953f05f177bc9b101-e3da20cfdca65c9db3a3.js.map
peacasso/web/backend/ui/404.html
peacasso/web/backend/ui/5a3f41a5-114c2828808e212157bf.js
peacasso/web/backend/ui/5a3f41a5-114c2828808e212157bf.js.map
peacasso/web/backend/ui/app-cbe708f9f558135fdae2.js
peacasso/web/backend/ui/app-cbe708f9f558135fdae2.js.map
peacasso/web/backend/ui/chunk-map.json
peacasso/web/backend/ui/component---src-pages-404-tsx-35860b35f750ed726c73.js
peacasso/web/backend/ui/component---src-pages-404-tsx-35860b35f750ed726c73.js.map
peacasso/web/backend/ui/component---src-pages-editor-tsx-664cdf67b397ad56b6de.js
peacasso/web/backend/ui/component---src-pages-editor-tsx-664cdf67b397ad56b6de.js.map
peacasso/web/backend/ui/component---src-pages-index-tsx-8ff085988aec1032475f.js
peacasso/web/backend/ui/component---src-pages-index-tsx-8ff085988aec1032475f.js.LICENSE.txt
peacasso/web/backend/ui/component---src-pages-index-tsx-8ff085988aec1032475f.js.map
peacasso/web/backend/ui/component---src-pages-login-tsx-6d62e7bf4912ab77a2b3.js
peacasso/web/backend/ui/component---src-pages-login-tsx-6d62e7bf4912ab77a2b3.js.map
peacasso/web/backend/ui/favicon-32x32.png
peacasso/web/backend/ui/framework-5b4618e8c160208ac157.js
peacasso/web/backend/ui/framework-5b4618e8c160208ac157.js.LICENSE.txt
peacasso/web/backend/ui/framework-5b4618e8c160208ac157.js.map
peacasso/web/backend/ui/index.html
peacasso/web/backend/ui/manifest.webmanifest
peacasso/web/backend/ui/polyfill-bf838d17a58468e595f2.js
peacasso-0.0.19a0.dist-info/LICENSE
peacasso-0.0.19a0.dist-info/METADATA
peacasso-0.0.19a0.dist-info/WHEEL
peacasso-0.0.19a0.dist-info/entry_points.txt
peacasso-0.0.19a0.dist-info/top_level.txt
peacasso-0.0.19a0.dist-info/RECORD
