Metadata-Version: 2.1
Name: peacasso
Version: 0.0.19a0
Summary: UI tool to help you generate art (and experiment) with multimodal (text, image) AI models (stable diffusion)
Author-email: Victor Dibia <victor.dibia@gmail.com>
License: MIT License
Project-URL: Homepage, https://github.com/victordibia/peacasso
Project-URL: Bug Tracker, https://github.com/victordibia/peacasso/issues
Classifier: Programming Language :: Python :: 3
Classifier: License :: OSI Approved :: MIT License
Classifier: Operating System :: OS Independent
Requires-Python: >=3.7
License-File: LICENSE
Requires-Dist: transformers
Requires-Dist: scipy
Requires-Dist: accelerate
Requires-Dist: ftfy
Requires-Dist: diffusers ==0.9.0
Requires-Dist: torch
Requires-Dist: pydantic
Requires-Dist: uvicorn
Requires-Dist: typer
Requires-Dist: fastapi
